pyclipmgr/__init__.py
pyclipmgr/pyclipmgr.py
pyclipmgr/bin/wl-copy
pyclipmgr/bin/wl-paste
pyclipmgr/bin/xclip
pyclipmgr-5.0.1.data/scripts/pyclipmgr.py
pyclipmgr-5.0.1.dist-info/LICENSE
pyclipmgr-5.0.1.dist-info/METADATA
pyclipmgr-5.0.1.dist-info/WHEEL
pyclipmgr-5.0.1.dist-info/top_level.txt
pyclipmgr-5.0.1.dist-info/RECORD
