Metadata-Version: 2.1
Name: pyclipmgr
Version: 5.0.1
Summary: this lib check for your machine's platform and use system commands to contact with clipboard (copy or paste) in python
Home-page: https://github.com/mohammed-saleh2007/py-clip-mgr
Author: sudo man
Author-email: supertechman@yahoo.com
License-File: LICENSE
